investops/__init__.py
investops/check.py
investops/constants.py
investops/diversify.py
investops/diversify_sparse.py
investops/group_constraints.py
investops/maps.py
investops/metrics.py
investops/normalize.py
investops/random.py
investops/rel_change.py
investops/remove_weights.py
investops/sparse.py
investops/stats.py
investops/stock_forecast.py
investops/utils.py
investops-0.4.0.dist-info/LICENSE
investops-0.4.0.dist-info/METADATA
investops-0.4.0.dist-info/WHEEL
investops-0.4.0.dist-info/top_level.txt
investops-0.4.0.dist-info/RECORD
